tiny_q.py
TinyQSim-1.1.dist-info/LICENSE
TinyQSim-1.1.dist-info/METADATA
TinyQSim-1.1.dist-info/WHEEL
TinyQSim-1.1.dist-info/top_level.txt
TinyQSim-1.1.dist-info/RECORD
