Metadata-Version: 2.1
Name: TinyQSim
Version: 1.1
Summary: A minimal framework to simulate quantum computation using matrix and tensor maths.
Home-page: https://github.com/Kahsolt/Tiny-Q
Author: Kahsolt
Author-email: kahsolt@qq.com
License: MIT
Classifier: Development Status :: 4 - Beta
Classifier: Environment :: Console
Classifier: Intended Audience :: Education
Classifier: Intended Audience :: Science/Research
Classifier: License :: OSI Approved :: MIT License
Classifier: Natural Language :: English
Classifier: Programming Language :: Python
Classifier: Programming Language :: Python :: 3
Classifier: Programming Language :: Python :: Implementation
Classifier: Programming Language :: Python :: Implementation :: CPython
Classifier: Programming Language :: Python :: Implementation :: PyPy
Classifier: Topic :: Education
Classifier: Topic :: Scientific/Engineering :: Mathematics
Classifier: Topic :: Scientific/Engineering :: Physics
Requires-Python: >=3.6.0
License-File: LICENSE
Requires-Dist: numpy
Requires-Dist: scipy
Provides-Extra: plot
Requires-Dist: matplotlib ; extra == 'plot'
Requires-Dist: seaborn ; extra == 'plot'
